unmango_baremetal/__init__.py
unmango_baremetal/_utilities.py
unmango_baremetal/command.py
unmango_baremetal/provider.py
unmango_baremetal/pulumi-plugin.json
unmango_baremetal/py.typed
unmango_baremetal/config/__init__.py
unmango_baremetal/config/__init__.pyi
unmango_baremetal/config/vars.py
unmango_baremetal/coreutils/__init__.py
unmango_baremetal/coreutils/_inputs.py
unmango_baremetal/coreutils/cat.py
unmango_baremetal/coreutils/chmod.py
unmango_baremetal/coreutils/mkdir.py
unmango_baremetal/coreutils/mktemp.py
unmango_baremetal/coreutils/mv.py
unmango_baremetal/coreutils/outputs.py
unmango_baremetal/coreutils/rm.py
unmango_baremetal/coreutils/tar.py
unmango_baremetal/coreutils/tee.py
unmango_baremetal/coreutils/wget.py
unmango_baremetal/kubeadm/__init__.py
unmango_baremetal/kubeadm/_inputs.py
unmango_baremetal/kubeadm/kubeadm.py
unmango_baremetal/kubeadm/outputs.py
unmango_baremetal-0.0.40.dist-info/METADATA
unmango_baremetal-0.0.40.dist-info/WHEEL
unmango_baremetal-0.0.40.dist-info/top_level.txt
unmango_baremetal-0.0.40.dist-info/RECORD
