Metadata-Version: 2.1
Name: unmango_baremetal
Version: 0.0.40
Requires-Python: >=3.8
Requires-Dist: parver >=0.2.1
Requires-Dist: pulumi <4.0.0,>=3.0.0
Requires-Dist: pulumi-command <2.0.0,>=1.0.0
Requires-Dist: semver >=2.8.1
